MANIFEST.in
README.md
setup.py
ddddsr/__init__.py
ddddsr/core.py
ddddsr.egg-info/PKG-INFO
ddddsr.egg-info/SOURCES.txt
ddddsr.egg-info/dependency_links.txt
ddddsr.egg-info/requires.txt
ddddsr.egg-info/top_level.txt
ddddsr/models/cunet/noise0_scale2.0x_model.onnx
ddddsr/models/cunet/noise1_scale2.0x_model.onnx
ddddsr/models/cunet/noise2_scale2.0x_model.onnx
ddddsr/models/cunet/noise3_scale2.0x_model.onnx
ddddsr/models/cunet/scale2.0x_model.onnx
ddddsr/models/upconv_7/noise0_scale2.0x_model.onnx
ddddsr/models/upconv_7/noise1_scale2.0x_model.onnx
ddddsr/models/upconv_7/noise2_scale2.0x_model.onnx
ddddsr/models/upconv_7/noise3_scale2.0x_model.onnx
ddddsr/models/upconv_7/scale2.0x_model.onnx
ddddsr/ppocronnx/__init__.py
ddddsr/ppocronnx/demo.py
ddddsr/ppocronnx/predict_system.py
ddddsr/ppocronnx/utility.py
ddddsr/ppocronnx/__pycache__/__init__.cpython-37.pyc
ddddsr/ppocronnx/__pycache__/predict_system.cpython-37.pyc
ddddsr/ppocronnx/__pycache__/utility.cpython-37.pyc
ddddsr/ppocronnx/cls/__init__.py
ddddsr/ppocronnx/cls/postprocess.py
ddddsr/ppocronnx/cls/predict_cls.py
ddddsr/ppocronnx/cls/__pycache__/__init__.cpython-37.pyc
ddddsr/ppocronnx/cls/__pycache__/postprocess.cpython-37.pyc
ddddsr/ppocronnx/cls/__pycache__/predict_cls.cpython-37.pyc
ddddsr/ppocronnx/det/__init__.py
ddddsr/ppocronnx/det/postprocess.py
ddddsr/ppocronnx/det/predict_det.py
ddddsr/ppocronnx/det/preprocess.py
ddddsr/ppocronnx/det/__pycache__/__init__.cpython-37.pyc
ddddsr/ppocronnx/det/__pycache__/postprocess.cpython-37.pyc
ddddsr/ppocronnx/det/__pycache__/predict_det.cpython-37.pyc
ddddsr/ppocronnx/det/__pycache__/preprocess.cpython-37.pyc
ddddsr/ppocronnx/models/ch_PP-OCRv2_det_infer.onnx
ddddsr/ppocronnx/models/cls-model.onnx
ddddsr/ppocronnx/models/ppocr_keys_v1.txt
ddddsr/ppocronnx/models/rec-model.onnx
ddddsr/ppocronnx/rec/__init__.py
ddddsr/ppocronnx/rec/predict_rec.py
ddddsr/ppocronnx/rec/rec_decoder.py
ddddsr/ppocronnx/rec/__pycache__/__init__.cpython-37.pyc
ddddsr/ppocronnx/rec/__pycache__/predict_rec.cpython-37.pyc
ddddsr/ppocronnx/rec/__pycache__/rec_decoder.cpython-37.pyc