Metadata-Version: 2.1
Name: ddddsr
Version: 0.1.5
Summary: end-to-end super resolution toolkit
Home-page: https://github.com/ashawkey/ddddsr
Author: kiui
Author-email: ashawkey1999@gmail.com
License: UNKNOWN
Keywords: deep learning,super resolution
Platform: UNKNOWN
Classifier: Intended Audience :: Science/Research
Classifier: Programming Language :: Python :: 3 
